<dataset>
  <title>Training Dataset</title>
  <images>
    <image file="s0014/s0014_06973_0_0_1_2_1_02.png" />
    <image file="s0014/s0014_06974_0_0_1_2_1_02.png" />
    <image file="s0014/s0014_06975_0_0_1_2_1_02.png" />
    <image file="s0014/s0014_06976_0_0_1_2_1_02.png" />
    <image file="s0014/s0014_06977_0_0_1_2_1_02.png" />
    <image file="s0014/s0014_06978_0_0_1_2_1_02.png" />
    <image file="s0014/s0014_06979_0_0_1_2_1_02.png" />
    <image file="s0014/s0014_06980_0_0_1_2_1_02.png" />
    <image file="s0014/s0014_06981_0_0_1_2_1_02.png" />
    <image file="s0014/s0014_06982_0_0_1_2_1_02.png" />
    <image file="s0014/s0014_06983_0_0_1_2_1_02.png" />
    <image file="s0014/s0014_06984_0_0_1_2_1_02.png" />
    <image file="s0014/s0014_06985_0_0_1_2_1_02.png" />
    <image file="s0014/s0014_06986_0_0_1_2_1_02.png" />
    <image file="s0014/s0014_06987_0_0_1_2_1_02.png" />
    <image file="s0014/s0014_06988_0_0_1_2_1_02.png" />
    <image file="s0014/s0014_06989_0_0_1_2_1_02.png" />
    <image file="s0014/s0014_06990_0_0_1_2_1_02.png" />
    <image file="s0014/s0014_06991_0_0_1_2_1_02.png" />
    <image file="s0014/s0014_06992_0_0_1_2_1_02.png" />
    <image file="s0014/s0014_06993_0_0_1_2_1_02.png" />
    <image file="s0014/s0014_06994_0_0_1_2_1_02.png" />
    <image file="s0014/s0014_06995_0_0_1_2_1_02.png" />
    <image file="s0014/s0014_06996_0_0_1_2_1_02.png" />
    <image file="s0014/s0014_06997_0_0_1_2_1_02.png" />
    <image file="s0014/s0014_06998_0_0_1_2_1_02.png" />
    <image file="s0014/s0014_06999_0_0_1_2_1_02.png" />
    <image file="s0014/s0014_07000_0_0_1_2_1_02.png" />
    <image file="s0014/s0014_07001_0_0_1_2_1_02.png" />
    <image file="s0014/s0014_07002_0_0_1_2_1_02.png" />
    <image file="s0014/s0014_07003_0_0_1_2_1_02.png" />
    <image file="s0014/s0014_07004_0_0_1_2_1_02.png" />
    <image file="s0014/s0014_07005_0_0_1_2_1_02.png" />
    <image file="s0014/s0014_07006_0_0_1_2_1_02.png" />
    <image file="s0014/s0014_07007_0_0_1_2_1_02.png" />
    <image file="s0014/s0014_07008_0_0_1_2_1_02.png" />
    <image file="s0014/s0014_07009_0_0_1_2_1_02.png" />
    <image file="s0014/s0014_07010_0_0_1_2_1_02.png" />
    <image file="s0014/s0014_07011_0_0_1_2_1_02.png" />
    <image file="s0014/s0014_07012_0_0_1_2_1_02.png" />
    <image file="s0014/s0014_07013_0_0_1_2_1_02.png" />
    <image file="s0014/s0014_07014_0_0_1_2_1_02.png" />
    <image file="s0014/s0014_07015_0_0_1_2_1_02.png" />
    <image file="s0014/s0014_07016_0_0_1_2_1_02.png" />
    <image file="s0014/s0014_07017_0_0_1_2_1_02.png" />
    <image file="s0014/s0014_07018_0_0_1_2_1_02.png" />
    <image file="s0014/s0014_07019_0_0_1_2_1_02.png" />
    <image file="s0014/s0014_07020_0_0_1_2_1_02.png" />
    <image file="s0014/s0014_07021_0_0_1_2_1_02.png" />
    <image file="s0014/s0014_07022_0_0_1_2_1_02.png" />
    <image file="s0014/s0014_07023_0_0_1_2_1_02.png" />
    <image file="s0014/s0014_07024_0_0_1_2_1_02.png" />
    <image file="s0014/s0014_07025_0_0_1_2_1_02.png" />
    <image file="s0014/s0014_07026_0_0_1_2_1_02.png" />
    <image file="s0014/s0014_07027_0_0_1_2_1_02.png" />
    <image file="s0014/s0014_07028_0_0_1_2_1_02.png" />
    <image file="s0014/s0014_07029_0_0_1_2_1_02.png" />
    <image file="s0014/s0014_07030_0_0_1_2_1_02.png" />
    <image file="s0014/s0014_07031_0_0_1_2_1_02.png" />
    <image file="s0014/s0014_07032_0_0_1_2_1_02.png" />
    <image file="s0014/s0014_07033_0_0_1_2_1_02.png" />
    <image file="s0014/s0014_07034_0_0_1_2_1_02.png" />
    <image file="s0014/s0014_07035_0_0_1_2_1_02.png" />
    <image file="s0014/s0014_07036_0_0_1_2_1_02.png" />
    <image file="s0014/s0014_07037_0_0_1_2_1_02.png" />
    <image file="s0014/s0014_07038_0_0_1_2_1_02.png" />
    <image file="s0014/s0014_07039_0_0_1_2_1_02.png" />
    <image file="s0014/s0014_07040_0_0_1_2_1_02.png" />
    <image file="s0014/s0014_07041_0_0_1_2_1_02.png" />
    <image file="s0014/s0014_07042_0_0_1_2_1_02.png" />
    <image file="s0014/s0014_07043_0_0_1_2_1_02.png" />
    <image file="s0014/s0014_07044_0_0_1_2_1_02.png" />
    <image file="s0014/s0014_07045_0_0_1_2_1_02.png" />
    <image file="s0014/s0014_07046_0_0_1_2_1_02.png" />
    <image file="s0014/s0014_07047_0_0_1_2_1_02.png" />
    <image file="s0014/s0014_07048_0_0_1_2_1_02.png" />
    <image file="s0014/s0014_07049_0_0_1_2_1_02.png" />
    <image file="s0014/s0014_07050_0_0_1_2_1_02.png" />
    <image file="s0014/s0014_07051_0_0_1_2_1_02.png" />
    <image file="s0014/s0014_07052_0_0_1_2_1_02.png" />
    <image file="s0014/s0014_07053_0_0_1_2_1_02.png" />
    <image file="s0014/s0014_07054_0_0_1_2_1_02.png" />
    <image file="s0014/s0014_07055_0_0_1_2_1_02.png" />
    <image file="s0014/s0014_07056_0_0_1_2_1_02.png" />
    <image file="s0014/s0014_07057_0_0_1_2_1_02.png" />
    <image file="s0014/s0014_07058_0_0_1_2_1_02.png" />
    <image file="s0014/s0014_07059_0_0_1_2_1_02.png" />
    <image file="s0014/s0014_07060_0_0_1_2_1_02.png" />
    <image file="s0014/s0014_07061_0_0_1_2_1_02.png" />
    <image file="s0014/s0014_07062_0_0_1_2_1_02.png" />
    <image file="s0014/s0014_07063_0_0_1_2_1_02.png" />
    <image file="s0014/s0014_07064_0_0_1_2_1_02.png" />
    <image file="s0014/s0014_07065_0_0_1_2_1_02.png" />
    <image file="s0014/s0014_07066_0_0_1_2_1_02.png" />
    <image file="s0014/s0014_07067_0_0_1_2_1_02.png" />
    <image file="s0014/s0014_07068_0_0_1_2_1_02.png" />
    <image file="s0014/s0014_07069_0_0_1_2_1_02.png" />
    <image file="s0014/s0014_07070_0_0_1_2_1_02.png" />
    <image file="s0014/s0014_07071_0_0_1_2_1_02.png" />
    <image file="s0014/s0014_07072_0_0_1_2_1_02.png" />
    <image file="s0014/s0014_07073_0_0_1_2_1_02.png" />
    <image file="s0014/s0014_07074_0_0_1_2_1_02.png" />
    <image file="s0014/s0014_07075_0_0_1_2_1_02.png" />
    <image file="s0014/s0014_07076_0_0_1_2_1_02.png" />
    <image file="s0014/s0014_07077_0_0_1_2_1_02.png" />
    <image file="s0014/s0014_07078_0_0_1_2_1_02.png" />
    <image file="s0014/s0014_07079_0_0_1_2_1_02.png" />
    <image file="s0014/s0014_07080_0_0_1_2_1_02.png" />
    <image file="s0014/s0014_07081_0_0_1_2_1_02.png" />
    <image file="s0014/s0014_07082_0_0_1_2_1_02.png" />
    <image file="s0014/s0014_07083_0_0_1_2_1_02.png" />
    <image file="s0014/s0014_07084_0_0_1_2_1_02.png" />
    <image file="s0014/s0014_07085_0_0_1_2_1_02.png" />
    <image file="s0014/s0014_07086_0_0_1_2_1_02.png" />
    <image file="s0014/s0014_07087_0_0_1_2_1_02.png" />
    <image file="s0014/s0014_07088_0_0_1_2_1_02.png" />
    <image file="s0014/s0014_07089_0_0_1_2_1_02.png" />
    <image file="s0014/s0014_07090_0_0_1_2_1_02.png" />
    <image file="s0014/s0014_07091_0_0_1_2_1_02.png" />
    <image file="s0014/s0014_07092_0_0_1_2_1_02.png" />
    <image file="s0014/s0014_07093_0_0_1_2_1_02.png" />
    <image file="s0014/s0014_07094_0_0_1_2_1_02.png" />
    <image file="s0014/s0014_07095_0_0_1_2_1_02.png" />
    <image file="s0014/s0014_07096_0_0_1_2_1_02.png" />
    <image file="s0014/s0014_07097_0_0_1_2_1_02.png" />
    <image file="s0014/s0014_07098_0_0_1_2_1_02.png" />
    <image file="s0014/s0014_07099_0_0_1_2_1_02.png" />
    <image file="s0014/s0014_07100_0_0_1_2_1_02.png" />
    <image file="s0014/s0014_07101_0_0_1_2_1_02.png" />
    <image file="s0014/s0014_07102_0_0_1_2_1_02.png" />
    <image file="s0014/s0014_07103_0_0_1_2_1_02.png" />
    <image file="s0014/s0014_07104_0_0_1_2_1_02.png" />
    <image file="s0014/s0014_07105_0_0_1_2_1_02.png" />
    <image file="s0014/s0014_07106_0_0_1_2_1_02.png" />
    <image file="s0014/s0014_07107_0_0_1_2_1_02.png" />
    <image file="s0014/s0014_07108_0_0_1_2_1_02.png" />
    <image file="s0014/s0014_07109_0_0_1_2_1_02.png" />
    <image file="s0014/s0014_07110_0_0_1_2_1_02.png" />
    <image file="s0014/s0014_07111_0_0_1_2_1_02.png" />
    <image file="s0014/s0014_07112_0_0_1_2_1_02.png" />
    <image file="s0014/s0014_07113_0_0_1_2_1_02.png" />
    <image file="s0014/s0014_07114_0_0_1_2_1_02.png" />
    <image file="s0014/s0014_07115_0_0_1_2_1_02.png" />
    <image file="s0014/s0014_07116_0_0_1_2_1_02.png" />
    <image file="s0014/s0014_07117_0_0_1_2_1_02.png" />
    <image file="s0014/s0014_07118_0_0_1_2_1_02.png" />
    <image file="s0014/s0014_07119_0_0_1_2_1_02.png" />
    <image file="s0014/s0014_07120_0_0_1_2_1_02.png" />
    <image file="s0014/s0014_07121_0_0_1_2_1_02.png" />
    <image file="s0014/s0014_07122_0_0_1_2_1_02.png" />
    <image file="s0014/s0014_07123_0_0_1_2_1_02.png" />
    <image file="s0014/s0014_07124_0_0_1_2_1_02.png" />
    <image file="s0014/s0014_07125_0_0_1_2_1_02.png" />
    <image file="s0014/s0014_07126_0_0_1_2_1_02.png" />
    <image file="s0014/s0014_07127_0_0_1_2_1_02.png" />
    <image file="s0014/s0014_07128_0_0_1_2_1_02.png" />
    <image file="s0014/s0014_07129_0_0_1_2_1_02.png" />
    <image file="s0014/s0014_07130_0_0_1_2_1_02.png" />
    <image file="s0014/s0014_07131_0_0_1_2_1_02.png" />
    <image file="s0014/s0014_07132_0_0_1_2_1_02.png" />
    <image file="s0014/s0014_07133_0_0_1_2_1_02.png" />
    <image file="s0014/s0014_07134_0_0_1_2_1_02.png" />
    <image file="s0014/s0014_07135_0_0_1_2_1_02.png" />
    <image file="s0014/s0014_07136_0_0_1_2_1_02.png" />
    <image file="s0014/s0014_07137_0_0_1_2_1_02.png" />
    <image file="s0014/s0014_07138_0_0_1_2_1_02.png" />
    <image file="s0014/s0014_07139_0_0_1_2_1_02.png" />
    <image file="s0014/s0014_07140_0_0_1_2_1_02.png" />
    <image file="s0014/s0014_07141_0_0_1_2_1_02.png" />
    <image file="s0014/s0014_07142_0_0_1_2_1_02.png" />
    <image file="s0014/s0014_07143_0_0_1_2_1_02.png" />
    <image file="s0014/s0014_07144_0_0_1_2_1_02.png" />
    <image file="s0014/s0014_07145_0_0_1_2_1_02.png" />
    <image file="s0014/s0014_07146_0_0_1_2_1_02.png" />
    <image file="s0014/s0014_07147_0_0_1_2_1_02.png" />
    <image file="s0014/s0014_07148_0_0_1_2_1_02.png" />
    <image file="s0014/s0014_07149_0_0_1_2_1_02.png" />
    <image file="s0014/s0014_07150_0_0_1_2_1_02.png" />
    <image file="s0014/s0014_07151_0_0_1_2_1_02.png" />
    <image file="s0014/s0014_07152_0_0_1_2_1_02.png" />
    <image file="s0014/s0014_07153_0_0_1_2_1_02.png" />
    <image file="s0014/s0014_07154_0_0_1_2_1_02.png" />
    <image file="s0014/s0014_07155_0_0_1_2_1_02.png" />
    <image file="s0014/s0014_07156_0_0_1_2_1_02.png" />
    <image file="s0014/s0014_07157_0_0_1_2_1_02.png" />
    <image file="s0014/s0014_07158_0_0_1_2_1_02.png" />
    <image file="s0014/s0014_07159_0_0_1_2_1_02.png" />
    <image file="s0014/s0014_07160_0_0_1_2_1_02.png" />
    <image file="s0014/s0014_07161_0_0_1_2_1_02.png" />
    <image file="s0014/s0014_07162_0_0_1_2_1_02.png" />
    <image file="s0014/s0014_07163_0_0_1_2_1_02.png" />
    <image file="s0014/s0014_07164_0_0_1_2_1_02.png" />
    <image file="s0014/s0014_07165_0_0_1_2_1_02.png" />
    <image file="s0014/s0014_07166_0_0_1_2_1_02.png" />
    <image file="s0014/s0014_07167_0_0_1_2_1_02.png" />
    <image file="s0014/s0014_07168_0_0_1_2_1_02.png" />
    <image file="s0014/s0014_07169_0_0_1_2_1_02.png" />
    <image file="s0014/s0014_07170_0_0_1_2_1_02.png" />
    <image file="s0014/s0014_07171_0_0_1_2_1_02.png" />
    <image file="s0014/s0014_07172_0_0_1_2_1_02.png" />
    <image file="s0014/s0014_07173_0_0_1_2_1_02.png" />
    <image file="s0014/s0014_07174_0_0_1_2_1_02.png" />
    <image file="s0014/s0014_07175_0_0_1_2_1_02.png" />
    <image file="s0014/s0014_07176_0_0_1_2_1_02.png" />
    <image file="s0014/s0014_07177_0_0_1_2_1_02.png" />
    <image file="s0014/s0014_07178_0_0_1_2_1_02.png" />
    <image file="s0014/s0014_07179_0_0_1_2_1_02.png" />
    <image file="s0014/s0014_07180_0_0_1_2_1_02.png" />
    <image file="s0014/s0014_07181_0_0_1_2_1_02.png" />
    <image file="s0014/s0014_07182_0_0_1_2_1_02.png" />
    <image file="s0014/s0014_07183_0_0_1_2_1_02.png" />
    <image file="s0014/s0014_07184_0_0_1_2_1_02.png" />
    <image file="s0014/s0014_07185_0_0_1_2_1_02.png" />
    <image file="s0014/s0014_07186_0_0_1_2_1_02.png" />
    <image file="s0014/s0014_07187_0_0_1_2_1_02.png" />
    <image file="s0014/s0014_07188_0_0_1_2_1_02.png" />
    <image file="s0014/s0014_07189_0_0_1_2_1_02.png" />
    <image file="s0014/s0014_07190_0_0_1_2_1_02.png" />
    <image file="s0014/s0014_07191_0_0_1_2_1_02.png" />
    <image file="s0014/s0014_07192_0_0_1_2_1_02.png" />
    <image file="s0014/s0014_07193_0_0_1_2_1_02.png" />
    <image file="s0014/s0014_07194_0_0_1_2_1_02.png" />
    <image file="s0014/s0014_07195_0_0_1_2_1_02.png" />
    <image file="s0014/s0014_07196_0_0_1_2_1_02.png" />
    <image file="s0014/s0014_07197_0_0_1_2_1_02.png" />
    <image file="s0014/s0014_07198_0_0_1_2_1_02.png" />
    <image file="s0014/s0014_07199_0_0_1_2_1_02.png" />
    <image file="s0014/s0014_07200_0_0_1_2_1_02.png" />
    <image file="s0014/s0014_07201_0_0_1_2_1_02.png" />
    <image file="s0014/s0014_07202_0_0_1_2_1_02.png" />
    <image file="s0014/s0014_07203_0_0_1_2_1_02.png" />
    <image file="s0014/s0014_07204_0_0_1_2_1_02.png" />
    <image file="s0014/s0014_07205_0_0_1_2_1_02.png" />
    <image file="s0014/s0014_07206_0_0_1_2_1_02.png" />
    <image file="s0014/s0014_07207_0_0_1_2_1_02.png" />
    <image file="s0014/s0014_07208_0_0_1_2_1_02.png" />
    <image file="s0014/s0014_07209_0_0_1_2_1_02.png" />
    <image file="s0014/s0014_07210_0_0_1_2_1_02.png" />
    <image file="s0014/s0014_07211_0_0_1_2_1_02.png" />
    <image file="s0014/s0014_07212_0_0_1_2_1_02.png" />
    <image file="s0014/s0014_07213_0_0_1_2_1_02.png" />
    <image file="s0014/s0014_07214_0_0_1_2_1_02.png" />
    <image file="s0014/s0014_07215_0_0_1_2_1_02.png" />
    <image file="s0014/s0014_07216_0_0_1_2_1_02.png" />
    <image file="s0014/s0014_07217_0_0_1_2_1_02.png" />
    <image file="s0014/s0014_07218_0_0_1_2_1_02.png" />
    <image file="s0014/s0014_07219_0_0_1_2_1_02.png" />
    <image file="s0014/s0014_07220_0_0_1_1_1_02.png" />
    <image file="s0014/s0014_07221_0_0_1_2_1_02.png" />
    <image file="s0014/s0014_07222_0_0_1_2_1_02.png" />
    <image file="s0014/s0014_07223_0_0_1_2_1_02.png" />
    <image file="s0014/s0014_07224_0_0_1_2_1_02.png" />
    <image file="s0014/s0014_07225_0_0_1_2_1_02.png" />
    <image file="s0014/s0014_07226_0_0_1_1_1_02.png" />
    <image file="s0014/s0014_07227_0_0_1_2_1_02.png" />
    <image file="s0014/s0014_07228_0_0_1_1_1_02.png" />
    <image file="s0014/s0014_07229_0_0_1_2_1_02.png" />
    <image file="s0014/s0014_07230_0_0_1_1_1_02.png" />
    <image file="s0014/s0014_07231_0_0_1_2_1_02.png" />
    <image file="s0014/s0014_07232_0_0_1_1_1_02.png" />
    <image file="s0014/s0014_07233_0_0_1_2_1_02.png" />
    <image file="s0014/s0014_07234_0_0_1_1_1_02.png" />
    <image file="s0014/s0014_07235_0_0_1_2_1_02.png" />
    <image file="s0014/s0014_07236_0_0_1_2_1_02.png" />
    <image file="s0014/s0014_07237_0_0_1_2_1_02.png" />
    <image file="s0014/s0014_07238_0_0_1_2_1_02.png" />
    <image file="s0014/s0014_07239_0_0_1_2_1_02.png" />
    <image file="s0014/s0014_07240_0_0_1_1_1_02.png" />
    <image file="s0014/s0014_07241_0_0_1_2_1_02.png" />
    <image file="s0014/s0014_07242_0_0_1_2_1_02.png" />
    <image file="s0014/s0014_07243_0_0_1_2_1_02.png" />
    <image file="s0014/s0014_07244_0_0_1_1_1_02.png" />
    <image file="s0014/s0014_07245_0_0_1_2_1_02.png" />
    <image file="s0014/s0014_07246_0_0_1_2_1_02.png" />
    <image file="s0014/s0014_07247_0_0_1_2_1_02.png" />
    <image file="s0014/s0014_07248_0_0_1_2_1_02.png" />
    <image file="s0014/s0014_07249_0_0_1_2_1_02.png" />
    <image file="s0014/s0014_07250_0_0_1_2_1_02.png" />
    <image file="s0014/s0014_07251_0_0_1_2_1_02.png" />
    <image file="s0014/s0014_07252_0_0_1_1_1_02.png" />
    <image file="s0014/s0014_07253_0_0_1_2_1_02.png" />
    <image file="s0014/s0014_07254_0_0_1_2_1_02.png" />
    <image file="s0014/s0014_07255_0_0_1_2_1_02.png" />
    <image file="s0014/s0014_07256_0_0_1_1_1_02.png" />
    <image file="s0014/s0014_07257_0_0_1_2_1_02.png" />
    <image file="s0014/s0014_07258_0_0_1_1_1_02.png" />
    <image file="s0014/s0014_07259_0_0_1_2_1_02.png" />
    <image file="s0014/s0014_07260_0_0_1_1_1_02.png" />
    <image file="s0014/s0014_07261_0_0_1_2_1_02.png" />
    <image file="s0014/s0014_07262_0_0_1_1_1_02.png" />
    <image file="s0014/s0014_07263_0_0_1_2_1_02.png" />
    <image file="s0014/s0014_07264_0_0_1_1_1_02.png" />
    <image file="s0014/s0014_07265_0_0_1_2_1_02.png" />
    <image file="s0014/s0014_07266_0_0_1_1_1_02.png" />
    <image file="s0014/s0014_07267_0_0_1_2_1_02.png" />
    <image file="s0014/s0014_07268_0_0_1_2_1_02.png" />
    <image file="s0014/s0014_07269_0_0_1_2_1_02.png" />
    <image file="s0014/s0014_07270_0_0_1_2_1_02.png" />
    <image file="s0014/s0014_07271_0_0_1_2_1_02.png" />
    <image file="s0014/s0014_07272_0_0_1_2_1_02.png" />
    <image file="s0014/s0014_07273_0_0_1_2_1_02.png" />
    <image file="s0014/s0014_07274_0_0_1_2_1_02.png" />
    <image file="s0014/s0014_07275_0_0_1_2_1_02.png" />
    <image file="s0014/s0014_07276_0_0_1_1_1_02.png" />
    <image file="s0014/s0014_07277_0_0_1_2_1_02.png" />
    <image file="s0014/s0014_07278_0_0_1_2_1_02.png" />
    <image file="s0014/s0014_07279_0_0_1_2_1_02.png" />
    <image file="s0014/s0014_07280_0_0_1_2_1_02.png" />
    <image file="s0014/s0014_07281_0_0_1_2_1_02.png" />
    <image file="s0014/s0014_07282_0_0_1_2_1_02.png" />
    <image file="s0014/s0014_07283_0_0_1_2_1_02.png" />
    <image file="s0014/s0014_07284_0_0_1_1_1_02.png" />
    <image file="s0014/s0014_07285_0_0_1_2_1_02.png" />
    <image file="s0014/s0014_07286_0_0_1_1_1_02.png" />
    <image file="s0014/s0014_07287_0_0_1_2_1_02.png" />
    <image file="s0014/s0014_07288_0_0_1_2_1_02.png" />
    <image file="s0014/s0014_07289_0_0_1_2_1_02.png" />
    <image file="s0014/s0014_07290_0_0_1_1_1_02.png" />
    <image file="s0014/s0014_07291_0_0_1_2_1_02.png" />
    <image file="s0014/s0014_07292_0_0_1_2_1_02.png" />
    <image file="s0014/s0014_07293_0_0_1_2_1_02.png" />
    <image file="s0014/s0014_07294_0_0_1_1_1_02.png" />
    <image file="s0014/s0014_07295_0_0_1_2_1_02.png" />
    <image file="s0014/s0014_07296_0_0_1_1_1_02.png" />
    <image file="s0014/s0014_07297_0_0_1_2_1_02.png" />
    <image file="s0014/s0014_07298_0_0_1_1_1_02.png" />
    <image file="s0014/s0014_07299_0_0_1_2_1_02.png" />
    <image file="s0014/s0014_07300_0_0_1_1_1_02.png" />
    <image file="s0014/s0014_07301_0_0_1_2_1_02.png" />
    <image file="s0014/s0014_07302_0_0_1_1_1_02.png" />
    <image file="s0014/s0014_07303_0_0_1_2_1_02.png" />
    <image file="s0014/s0014_07304_0_0_1_1_1_02.png" />
    <image file="s0014/s0014_07305_0_0_1_2_1_02.png" />
    <image file="s0014/s0014_07306_0_0_1_2_1_02.png" />
    <image file="s0014/s0014_07307_0_0_1_2_1_02.png" />
    <image file="s0014/s0014_07308_0_0_1_2_1_02.png" />
    <image file="s0014/s0014_07309_0_0_1_2_1_02.png" />
    <image file="s0014/s0014_07310_0_0_1_2_1_02.png" />
    <image file="s0014/s0014_07311_0_0_1_2_1_02.png" />
    <image file="s0014/s0014_07312_0_0_1_2_1_02.png" />
    <image file="s0014/s0014_07313_0_0_1_2_1_02.png" />
    <image file="s0014/s0014_07314_0_0_1_2_1_02.png" />
    <image file="s0014/s0014_07315_0_0_1_2_1_02.png" />
    <image file="s0014/s0014_07316_0_0_1_1_1_02.png" />
    <image file="s0014/s0014_07317_0_0_1_2_1_02.png" />
    <image file="s0014/s0014_07318_0_0_1_2_1_02.png" />
    <image file="s0014/s0014_07319_0_0_1_2_1_02.png" />
    <image file="s0014/s0014_07320_0_0_1_1_1_02.png" />
    <image file="s0014/s0014_07321_0_0_1_2_1_02.png" />
    <image file="s0014/s0014_07322_0_0_1_1_1_02.png" />
    <image file="s0014/s0014_07323_0_0_1_2_1_02.png" />
    <image file="s0014/s0014_07324_0_0_1_1_1_02.png" />
    <image file="s0014/s0014_07325_0_0_1_2_1_02.png" />
    <image file="s0014/s0014_07326_0_0_1_1_1_02.png" />
    <image file="s0014/s0014_07327_0_0_1_2_1_02.png" />
    <image file="s0014/s0014_07328_0_0_1_1_1_02.png" />
    <image file="s0014/s0014_07329_0_0_1_2_1_02.png" />
    <image file="s0014/s0014_07330_0_0_1_1_1_02.png" />
    <image file="s0014/s0014_07331_0_0_1_2_1_02.png" />
    <image file="s0014/s0014_07332_0_0_1_2_1_02.png" />
    <image file="s0014/s0014_07333_0_0_1_2_1_02.png" />
    <image file="s0014/s0014_07334_0_0_1_1_1_02.png" />
    <image file="s0014/s0014_07335_0_0_1_2_1_02.png" />
    <image file="s0014/s0014_07336_0_0_1_1_1_02.png" />
    <image file="s0014/s0014_07337_0_0_1_2_1_02.png" />
    <image file="s0014/s0014_07338_0_0_1_2_1_02.png" />
    <image file="s0014/s0014_07339_0_0_1_2_1_02.png" />
    <image file="s0014/s0014_07340_0_0_1_1_1_02.png" />
    <image file="s0014/s0014_07341_0_0_1_2_1_02.png" />
    <image file="s0014/s0014_07342_0_0_1_1_1_02.png" />
    <image file="s0014/s0014_07343_0_0_1_2_1_02.png" />
    <image file="s0014/s0014_07344_0_0_1_1_1_02.png" />
    <image file="s0014/s0014_07345_0_0_1_2_1_02.png" />
    <image file="s0014/s0014_07346_0_0_1_1_1_02.png" />
    <image file="s0014/s0014_07347_0_0_1_2_1_02.png" />
    <image file="s0014/s0014_07348_0_0_1_1_1_02.png" />
    <image file="s0014/s0014_07349_0_0_1_2_1_02.png" />
    <image file="s0014/s0014_07350_0_0_1_1_1_02.png" />
    <image file="s0014/s0014_07351_0_0_1_2_1_02.png" />
    <image file="s0014/s0014_07352_0_0_1_1_1_02.png" />
    <image file="s0014/s0014_07353_0_0_1_2_1_02.png" />
    <image file="s0014/s0014_07354_0_0_1_1_1_02.png" />
    <image file="s0014/s0014_07355_0_0_1_2_1_02.png" />
    <image file="s0014/s0014_07356_0_0_1_1_1_02.png" />
    <image file="s0014/s0014_07357_0_0_1_2_1_02.png" />
    <image file="s0014/s0014_07358_0_0_1_1_1_02.png" />
    <image file="s0014/s0014_07359_0_0_1_2_1_02.png" />
    <image file="s0014/s0014_07360_0_0_1_1_1_02.png" />
    <image file="s0014/s0014_07361_0_0_1_2_1_02.png" />
    <image file="s0014/s0014_07362_0_0_1_1_1_02.png" />
    <image file="s0014/s0014_07363_0_0_1_2_1_02.png" />
    <image file="s0014/s0014_07364_0_0_1_1_1_02.png" />
    <image file="s0014/s0014_07365_0_0_1_2_1_02.png" />
    <image file="s0014/s0014_07366_0_0_1_1_1_02.png" />
    <image file="s0014/s0014_07367_0_0_1_2_1_02.png" />
    <image file="s0014/s0014_07368_0_0_1_1_1_02.png" />
    <image file="s0014/s0014_07369_0_0_1_2_1_02.png" />
    <image file="s0014/s0014_07370_0_0_1_1_1_02.png" />
    <image file="s0014/s0014_07371_0_0_1_2_1_02.png" />
    <image file="s0014/s0014_07372_0_0_1_1_1_02.png" />
    <image file="s0014/s0014_07373_0_0_1_2_1_02.png" />
    <image file="s0014/s0014_07374_0_0_1_1_1_02.png" />
    <image file="s0014/s0014_07375_0_0_1_2_1_02.png" />
    <image file="s0014/s0014_07376_0_0_1_2_1_02.png" />
    <image file="s0014/s0014_07377_0_0_1_2_1_02.png" />
    <image file="s0014/s0014_07378_0_0_1_1_1_02.png" />
    <image file="s0014/s0014_07379_0_0_1_2_1_02.png" />
    <image file="s0014/s0014_07380_0_0_1_2_1_02.png" />
    <image file="s0014/s0014_07381_0_0_1_2_1_02.png" />
    <image file="s0014/s0014_07382_0_0_1_1_1_02.png" />
    <image file="s0014/s0014_07383_0_0_1_2_1_02.png" />
    <image file="s0014/s0014_07384_0_0_1_2_1_02.png" />
    <image file="s0014/s0014_07385_0_0_1_2_1_02.png" />
    <image file="s0014/s0014_07386_0_0_1_2_1_02.png" />
    <image file="s0014/s0014_07387_0_0_1_2_1_02.png" />
    <image file="s0014/s0014_07388_0_0_1_2_1_02.png" />
    <image file="s0014/s0014_07389_0_0_1_2_1_02.png" />
    <image file="s0014/s0014_07390_0_0_1_1_1_02.png" />
    <image file="s0014/s0014_07391_0_0_1_2_1_02.png" />
    <image file="s0014/s0014_07392_0_0_1_2_1_02.png" />
    <image file="s0014/s0014_07393_0_0_1_2_1_02.png" />
    <image file="s0014/s0014_07394_0_0_1_1_1_02.png" />
    <image file="s0014/s0014_07395_0_0_1_2_1_02.png" />
    <image file="s0014/s0014_07396_0_0_1_2_1_02.png" />
    <image file="s0014/s0014_07397_0_0_1_2_1_02.png" />
    <image file="s0014/s0014_07398_0_0_1_2_1_02.png" />
    <image file="s0014/s0014_07399_0_0_1_2_1_02.png" />
    <image file="s0014/s0014_07400_0_0_1_2_1_02.png" />
    <image file="s0014/s0014_07401_0_0_1_2_1_02.png" />
    <image file="s0014/s0014_07402_0_0_1_1_1_02.png" />
    <image file="s0014/s0014_07403_0_0_1_2_1_02.png" />
    <image file="s0014/s0014_07404_0_0_1_2_1_02.png" />
    <image file="s0014/s0014_07405_0_0_1_2_1_02.png" />
    <image file="s0014/s0014_07406_0_0_1_2_1_02.png" />
    <image file="s0014/s0014_07407_0_0_1_2_1_02.png" />
    <image file="s0014/s0014_07408_0_0_1_2_1_02.png" />
    <image file="s0014/s0014_07409_0_0_1_2_1_02.png" />
    <image file="s0014/s0014_07410_0_0_1_2_1_02.png" />
    <image file="s0014/s0014_07411_0_0_1_2_1_02.png" />
    <image file="s0014/s0014_07412_0_0_1_2_1_02.png" />
    <image file="s0014/s0014_07413_0_0_1_2_1_02.png" />
    <image file="s0014/s0014_07414_0_0_1_2_1_02.png" />
    <image file="s0014/s0014_07415_0_0_1_2_1_02.png" />
    <image file="s0014/s0014_07416_0_0_1_2_1_02.png" />
    <image file="s0014/s0014_07417_0_0_1_2_1_02.png" />
    <image file="s0014/s0014_07418_0_0_1_2_1_02.png" />
    <image file="s0014/s0014_07419_0_0_1_2_1_02.png" />
    <image file="s0014/s0014_07420_0_0_1_2_1_02.png" />
    <image file="s0014/s0014_07421_0_0_1_2_1_02.png" />
    <image file="s0014/s0014_07422_0_0_1_1_1_02.png" />
    <image file="s0014/s0014_07423_0_0_1_2_1_02.png" />
    <image file="s0014/s0014_07424_0_0_1_2_1_02.png" />
    <image file="s0014/s0014_07425_0_0_1_2_1_02.png" />
    <image file="s0014/s0014_07426_0_0_1_2_1_02.png" />
    <image file="s0014/s0014_07427_0_0_1_2_1_02.png" />
    <image file="s0014/s0014_07428_0_0_1_2_1_02.png" />
    <image file="s0014/s0014_07429_0_0_1_2_1_02.png" />
    <image file="s0014/s0014_07430_0_0_1_2_1_02.png" />
    <image file="s0014/s0014_07431_0_0_1_2_1_02.png" />
    <image file="s0014/s0014_07432_0_0_1_2_1_02.png" />
    <image file="s0014/s0014_07433_0_0_1_2_1_02.png" />
    <image file="s0014/s0014_07434_0_0_1_2_1_02.png" />
    <image file="s0014/s0014_07435_0_0_1_2_1_02.png" />
    <image file="s0014/s0014_07436_0_0_1_2_1_02.png" />
    <image file="s0014/s0014_07437_0_0_1_2_1_02.png" />
    <image file="s0014/s0014_07438_0_0_1_2_1_02.png" />
    <image file="s0014/s0014_07439_0_0_1_2_1_02.png" />
    <image file="s0014/s0014_07440_0_0_1_1_1_02.png" />
    <image file="s0014/s0014_07441_0_0_1_2_1_02.png" />
    <image file="s0014/s0014_07442_0_0_1_2_1_02.png" />
    <image file="s0014/s0014_07443_0_0_1_2_1_02.png" />
    <image file="s0014/s0014_07444_0_0_1_2_1_02.png" />
    <image file="s0014/s0014_07445_0_0_1_2_1_02.png" />
    <image file="s0014/s0014_07446_0_0_1_2_1_02.png" />
    <image file="s0014/s0014_07447_0_0_1_2_1_02.png" />
    <image file="s0014/s0014_07448_0_0_1_2_1_02.png" />
    <image file="s0014/s0014_07449_0_0_1_2_1_02.png" />
    <image file="s0014/s0014_07450_0_0_1_1_1_02.png" />
    <image file="s0014/s0014_07451_0_0_1_2_1_02.png" />
    <image file="s0014/s0014_07452_0_0_1_2_1_02.png" />
    <image file="s0014/s0014_07453_0_0_1_2_1_02.png" />
    <image file="s0014/s0014_07454_0_0_1_2_1_02.png" />
    <image file="s0014/s0014_07455_0_0_1_2_1_02.png" />
    <image file="s0014/s0014_07456_0_0_1_2_1_02.png" />
    <image file="s0014/s0014_07457_0_0_1_2_1_02.png" />
    <image file="s0014/s0014_07458_0_0_1_2_1_02.png" />
    <image file="s0014/s0014_07459_0_0_1_2_1_02.png" />
    <image file="s0014/s0014_07460_0_0_1_2_1_02.png" />
    <image file="s0014/s0014_07461_0_0_1_2_1_02.png" />
    <image file="s0014/s0014_07462_0_0_1_2_1_02.png" />
    <image file="s0014/s0014_07463_0_0_1_2_1_02.png" />
    <image file="s0014/s0014_07464_0_0_1_2_1_02.png" />
    <image file="s0014/s0014_07465_0_0_1_2_1_02.png" />
    <image file="s0014/s0014_07466_0_0_1_2_1_02.png" />
    <image file="s0014/s0014_07467_0_0_1_2_1_02.png" />
    <image file="s0014/s0014_07468_0_0_1_2_1_02.png" />
    <image file="s0014/s0014_07469_0_0_1_2_1_02.png" />
    <image file="s0014/s0014_07470_0_0_1_2_1_02.png" />
    <image file="s0014/s0014_07471_0_0_1_2_1_02.png" />
    <image file="s0014/s0014_07472_0_0_1_2_1_02.png" />
    <image file="s0014/s0014_07473_0_0_1_2_1_02.png" />
    <image file="s0014/s0014_07474_0_0_1_2_1_02.png" />
    <image file="s0014/s0014_07475_0_0_1_2_1_02.png" />
    <image file="s0014/s0014_07476_0_0_1_2_1_02.png" />
    <image file="s0014/s0014_07477_0_0_1_2_1_02.png" />
    <image file="s0014/s0014_07478_0_0_1_2_1_02.png" />
    <image file="s0014/s0014_07479_0_0_1_2_1_02.png" />
    <image file="s0014/s0014_07480_0_0_1_2_1_02.png" />
    <image file="s0014/s0014_07481_0_0_1_2_1_02.png" />
    <image file="s0014/s0014_07482_0_0_1_2_1_02.png" />
    <image file="s0014/s0014_07483_0_0_1_2_1_02.png" />
    <image file="s0014/s0014_07484_0_0_1_2_1_02.png" />
    <image file="s0014/s0014_07485_0_0_1_2_1_02.png" />
    <image file="s0014/s0014_07486_0_0_1_2_1_02.png" />
    <image file="s0014/s0014_07487_0_0_1_2_1_02.png" />
    <image file="s0014/s0014_07488_0_0_1_2_1_02.png" />
    <image file="s0014/s0014_07489_0_0_1_2_1_02.png" />
    <image file="s0014/s0014_07490_0_0_1_2_1_02.png" />
    <image file="s0014/s0014_07491_0_0_1_2_1_02.png" />
    <image file="s0014/s0014_07492_0_0_1_2_1_02.png" />
    <image file="s0014/s0014_07493_0_0_1_2_1_02.png" />
    <image file="s0014/s0014_07494_0_0_1_2_1_02.png" />
    <image file="s0014/s0014_07495_0_0_1_2_1_02.png" />
    <image file="s0014/s0014_07496_0_0_1_2_1_02.png" />
    <image file="s0014/s0014_07497_0_0_1_2_1_02.png" />
    <image file="s0014/s0014_07498_0_0_1_2_1_02.png" />
    <image file="s0014/s0014_07499_0_0_1_2_1_02.png" />
    <image file="s0014/s0014_07500_0_0_1_2_1_02.png" />
    <image file="s0014/s0014_07501_0_0_1_2_1_02.png" />
    <image file="s0014/s0014_07502_0_0_1_2_1_02.png" />
    <image file="s0014/s0014_07503_0_0_1_2_1_02.png" />
    <image file="s0014/s0014_07504_0_0_1_2_1_02.png" />
    <image file="s0014/s0014_07505_0_0_1_2_1_02.png" />
    <image file="s0014/s0014_07506_0_0_1_2_1_02.png" />
    <image file="s0014/s0014_07507_0_0_1_2_1_02.png" />
    <image file="s0014/s0014_07508_0_0_1_2_1_02.png" />
    <image file="s0014/s0014_07509_0_0_1_2_1_02.png" />
    <image file="s0014/s0014_07510_0_0_1_2_1_02.png" />
    <image file="s0014/s0014_07511_0_0_1_2_1_02.png" />
    <image file="s0014/s0014_07512_0_0_1_2_1_02.png" />
    <image file="s0014/s0014_07513_0_0_1_2_1_02.png" />
    <image file="s0014/s0014_07514_0_0_1_2_1_02.png" />
    <image file="s0014/s0014_07515_0_0_1_2_1_02.png" />
    <image file="s0014/s0014_07516_0_0_1_2_1_02.png" />
    <image file="s0014/s0014_07517_0_0_1_2_1_02.png" />
    <image file="s0014/s0014_07518_0_0_1_2_1_02.png" />
    <image file="s0014/s0014_07519_0_0_1_2_1_02.png" />
    <image file="s0014/s0014_07520_0_0_1_2_1_02.png" />
    <image file="s0014/s0014_07521_0_0_1_2_1_02.png" />
    <image file="s0014/s0014_07522_0_0_1_2_1_02.png" />
    <image file="s0014/s0014_07523_0_0_1_2_1_02.png" />
    <image file="s0014/s0014_07524_0_0_1_2_1_02.png" />
    <image file="s0014/s0014_07525_0_0_1_2_1_02.png" />
    <image file="s0014/s0014_07526_0_0_1_2_1_02.png" />
    <image file="s0014/s0014_07527_0_0_1_2_1_02.png" />
    <image file="s0014/s0014_07528_0_0_1_2_1_02.png" />
    <image file="s0014/s0014_07529_0_0_1_2_1_02.png" />
    <image file="s0014/s0014_07530_0_0_1_2_1_02.png" />
    <image file="s0014/s0014_07531_0_0_1_2_1_02.png" />
    <image file="s0014/s0014_07532_0_0_1_2_1_02.png" />
    <image file="s0014/s0014_07533_0_0_1_2_1_02.png" />
    <image file="s0014/s0014_07534_0_0_1_2_1_02.png" />
    <image file="s0014/s0014_07535_0_0_1_2_1_02.png" />
    <image file="s0014/s0014_07536_0_0_1_2_1_02.png" />
    <image file="s0014/s0014_07537_0_0_1_2_1_02.png" />
    <image file="s0014/s0014_07538_0_0_1_2_1_02.png" />
    <image file="s0014/s0014_07539_0_0_1_2_1_02.png" />
    <image file="s0014/s0014_07540_0_0_1_2_1_02.png" />
    <image file="s0014/s0014_07541_0_0_1_2_1_02.png" />
    <image file="s0014/s0014_07542_0_0_1_2_1_02.png" />
    <image file="s0014/s0014_07543_0_0_1_2_1_02.png" />
    <image file="s0014/s0014_07544_0_0_1_2_1_02.png" />
    <image file="s0014/s0014_07545_0_0_1_2_1_02.png" />
    <image file="s0014/s0014_07546_0_0_1_2_1_02.png" />
    <image file="s0014/s0014_07547_0_0_1_2_1_02.png" />
    <image file="s0014/s0014_07548_0_0_1_2_1_02.png" />
    <image file="s0014/s0014_07549_0_0_1_2_1_02.png" />
    <image file="s0014/s0014_07550_0_0_1_2_1_02.png" />
    <image file="s0014/s0014_07551_0_0_1_2_1_02.png" />
    <image file="s0014/s0014_07552_0_0_1_2_1_02.png" />
    <image file="s0014/s0014_07553_0_0_1_2_1_02.png" />
    <image file="s0014/s0014_07554_0_0_1_2_1_02.png" />
    <image file="s0014/s0014_07555_0_0_1_2_1_02.png" />
    <image file="s0014/s0014_07556_0_0_1_2_1_02.png" />
    <image file="s0014/s0014_07557_0_0_1_2_1_02.png" />
    <image file="s0014/s0014_07558_0_0_1_2_1_02.png" />
    <image file="s0014/s0014_07559_0_0_1_2_1_02.png" />
    <image file="s0014/s0014_07560_0_0_1_2_1_02.png" />
    <image file="s0014/s0014_07561_0_0_1_2_1_02.png" />
    <image file="s0014/s0014_07562_0_0_1_2_1_02.png" />
    <image file="s0014/s0014_07563_0_0_1_2_1_02.png" />
    <image file="s0014/s0014_07564_0_0_1_2_1_02.png" />
    <image file="s0014/s0014_07565_0_0_1_2_1_02.png" />
    <image file="s0014/s0014_07566_0_0_1_2_1_02.png" />
    <image file="s0014/s0014_07567_0_0_1_2_1_02.png" />
    <image file="s0014/s0014_07568_0_0_1_2_1_02.png" />
    <image file="s0014/s0014_07569_0_0_1_2_1_02.png" />
    <image file="s0014/s0014_07570_0_0_1_2_1_02.png" />
    <image file="s0014/s0014_07571_0_0_1_2_1_02.png" />
    <image file="s0014/s0014_07572_0_0_1_2_1_02.png" />
    <image file="s0014/s0014_07573_0_0_1_2_1_02.png" />
    <image file="s0014/s0014_07574_0_0_1_2_1_02.png" />
    <image file="s0014/s0014_07575_0_0_1_2_1_02.png" />
    <image file="s0014/s0014_07576_0_0_1_2_1_02.png" />
    <image file="s0014/s0014_07577_0_0_1_2_1_02.png" />
    <image file="s0014/s0014_07578_0_0_1_2_1_02.png" />
    <image file="s0014/s0014_07579_0_0_1_2_1_02.png" />
    <image file="s0014/s0014_07580_0_0_1_2_1_02.png" />
    <image file="s0014/s0014_07581_0_0_1_2_1_02.png" />
    <image file="s0014/s0014_07582_0_0_1_2_1_02.png" />
    <image file="s0014/s0014_07583_0_0_1_2_1_02.png" />
    <image file="s0014/s0014_07584_0_0_1_2_1_02.png" />
    <image file="s0014/s0014_07585_0_0_1_2_1_02.png" />
    <image file="s0014/s0014_07586_0_0_1_2_1_02.png" />
    <image file="s0014/s0014_07587_0_0_1_2_1_02.png" />
    <image file="s0014/s0014_07588_0_0_1_2_1_02.png" />
    <image file="s0014/s0014_07589_0_0_1_2_1_02.png" />
    <image file="s0014/s0014_07590_0_0_1_2_1_02.png" />
    <image file="s0014/s0014_07591_0_0_1_2_1_02.png" />
    <image file="s0014/s0014_07592_0_0_1_2_1_02.png" />
    <image file="s0014/s0014_07593_0_0_1_2_1_02.png" />
    <image file="s0014/s0014_07594_0_0_1_2_1_02.png" />
    <image file="s0014/s0014_07595_0_0_1_2_1_02.png" />
    <image file="s0014/s0014_07596_0_0_1_2_1_02.png" />
    <image file="s0014/s0014_07597_0_0_1_2_1_02.png" />
    <image file="s0014/s0014_07598_0_0_1_2_1_02.png" />
    <image file="s0014/s0014_07599_0_0_1_2_1_02.png" />
    <image file="s0014/s0014_07600_0_0_1_2_1_02.png" />
    <image file="s0014/s0014_07601_0_0_1_2_1_02.png" />
    <image file="s0014/s0014_07602_0_0_1_2_1_02.png" />
    <image file="s0014/s0014_07603_0_0_1_2_1_02.png" />
    <image file="s0014/s0014_07604_0_0_1_2_1_02.png" />
    <image file="s0014/s0014_07605_0_0_1_2_1_02.png" />
    <image file="s0014/s0014_07606_0_0_1_2_1_02.png" />
    <image file="s0014/s0014_07607_0_0_1_2_1_02.png" />
    <image file="s0014/s0014_07608_0_0_1_2_1_02.png" />
    <image file="s0014/s0014_07609_0_0_1_2_1_02.png" />
    <image file="s0014/s0014_07610_0_0_1_2_1_02.png" />
    <image file="s0014/s0014_07611_0_0_1_2_1_02.png" />
    <image file="s0014/s0014_07612_0_0_1_2_1_02.png" />
    <image file="s0014/s0014_07613_0_0_1_2_1_02.png" />
    <image file="s0014/s0014_07614_0_0_1_2_1_02.png" />
    <image file="s0014/s0014_07615_0_0_1_2_1_02.png" />
    <image file="s0014/s0014_07616_0_0_1_2_1_02.png" />
    <image file="s0014/s0014_07617_0_0_1_2_1_02.png" />
    <image file="s0014/s0014_07618_0_0_1_2_1_02.png" />
    <image file="s0014/s0014_07619_0_0_1_2_1_02.png" />
    <image file="s0014/s0014_07620_0_0_1_2_1_02.png" />
    <image file="s0014/s0014_07621_0_0_1_2_1_02.png" />
    <image file="s0014/s0014_07622_0_0_1_2_1_02.png" />
    <image file="s0014/s0014_07623_0_0_1_2_1_02.png" />
    <image file="s0014/s0014_07624_0_0_1_2_1_02.png" />
    <image file="s0014/s0014_07625_0_0_1_2_1_02.png" />
    <image file="s0014/s0014_07626_0_0_1_2_1_02.png" />
    <image file="s0014/s0014_07627_0_0_1_2_1_02.png" />
    <image file="s0014/s0014_07628_0_0_1_2_1_02.png" />
    <image file="s0014/s0014_07629_0_0_1_2_1_02.png" />
    <image file="s0014/s0014_07630_0_0_1_2_1_02.png" />
    <image file="s0014/s0014_07631_0_0_1_2_1_02.png" />
    <image file="s0014/s0014_07632_0_0_1_2_1_02.png" />
    <image file="s0014/s0014_07633_0_0_1_2_1_02.png" />
    <image file="s0014/s0014_07634_0_0_1_2_1_02.png" />
    <image file="s0014/s0014_07635_0_0_1_2_1_02.png" />
    <image file="s0014/s0014_07636_0_0_1_2_1_02.png" />
    <image file="s0014/s0014_07637_0_0_1_2_1_02.png" />
    <image file="s0014/s0014_07638_0_0_1_2_1_02.png" />
    <image file="s0014/s0014_07639_0_0_1_0_1_02.png" />
    <image file="s0014/s0014_07640_0_0_1_1_1_02.png" />
    <image file="s0014/s0014_07641_0_0_1_1_1_02.png" />
    <image file="s0014/s0014_07642_0_0_1_1_0_02.png" />
    <image file="s0014/s0014_07643_0_0_1_1_1_02.png" />
    <image file="s0014/s0014_07644_0_0_1_1_0_02.png" />
    <image file="s0014/s0014_07645_0_0_1_1_1_02.png" />
    <image file="s0014/s0014_07646_0_0_1_1_0_02.png" />
    <image file="s0014/s0014_07647_0_0_1_0_1_02.png" />
    <image file="s0014/s0014_07648_0_0_1_1_0_02.png" />
    <image file="s0014/s0014_07649_0_0_1_1_1_02.png" />
    <image file="s0014/s0014_07650_0_0_1_1_0_02.png" />
    <image file="s0014/s0014_07651_0_0_1_1_1_02.png" />
    <image file="s0014/s0014_07652_0_0_1_1_0_02.png" />
    <image file="s0014/s0014_07653_0_0_1_1_1_02.png" />
    <image file="s0014/s0014_07654_0_0_1_1_0_02.png" />
    <image file="s0014/s0014_07655_0_0_1_1_1_02.png" />
    <image file="s0014/s0014_07656_0_0_1_1_0_02.png" />
    <image file="s0014/s0014_07657_0_0_1_0_1_02.png" />
    <image file="s0014/s0014_07658_0_0_1_1_0_02.png" />
    <image file="s0014/s0014_07659_0_0_1_1_0_02.png" />
    <image file="s0014/s0014_07660_0_0_1_1_1_02.png" />
    <image file="s0014/s0014_07661_0_0_1_1_1_02.png" />
    <image file="s0014/s0014_07662_0_0_1_1_0_02.png" />
    <image file="s0014/s0014_07663_0_0_1_1_1_02.png" />
    <image file="s0014/s0014_07664_0_0_1_1_0_02.png" />
    <image file="s0014/s0014_07665_0_0_1_1_1_02.png" />
    <image file="s0014/s0014_07666_0_0_1_1_0_02.png" />
    <image file="s0014/s0014_07667_0_0_1_1_1_02.png" />
    <image file="s0014/s0014_07668_0_0_1_1_0_02.png" />
    <image file="s0014/s0014_07669_0_0_1_1_1_02.png" />
    <image file="s0014/s0014_07670_0_0_1_1_0_02.png" />
    <image file="s0014/s0014_07671_0_0_1_1_1_02.png" />
    <image file="s0014/s0014_07672_0_0_1_1_0_02.png" />
    <image file="s0014/s0014_07673_0_0_1_1_1_02.png" />
    <image file="s0014/s0014_07674_0_0_1_1_0_02.png" />
    <image file="s0014/s0014_07675_0_0_1_1_1_02.png" />
    <image file="s0014/s0014_07676_0_0_1_1_0_02.png" />
    <image file="s0014/s0014_07677_0_0_1_1_1_02.png" />
    <image file="s0014/s0014_07678_0_0_1_1_0_02.png" />
    <image file="s0014/s0014_07679_0_0_1_0_1_02.png" />
    <image file="s0014/s0014_07680_0_0_1_1_0_02.png" />
    <image file="s0014/s0014_07681_0_0_1_1_1_02.png" />
    <image file="s0014/s0014_07682_0_0_1_1_0_02.png" />
    <image file="s0014/s0014_07683_0_0_1_1_1_02.png" />
    <image file="s0014/s0014_07684_0_0_1_1_0_02.png" />
    <image file="s0014/s0014_07685_0_0_1_1_1_02.png" />
    <image file="s0014/s0014_07686_0_0_1_1_0_02.png" />
    <image file="s0014/s0014_07687_0_0_1_1_0_02.png" />
    <image file="s0014/s0014_07688_0_0_1_1_1_02.png" />
    <image file="s0014/s0014_07689_0_0_1_1_0_02.png" />
    <image file="s0014/s0014_07690_0_0_1_1_1_02.png" />
    <image file="s0014/s0014_07691_0_0_1_1_0_02.png" />
    <image file="s0014/s0014_07692_0_0_1_0_1_02.png" />
    <image file="s0014/s0014_07693_0_0_1_1_1_02.png" />
    <image file="s0014/s0014_07694_0_0_1_1_0_02.png" />
    <image file="s0014/s0014_07695_0_0_1_1_0_02.png" />
    <image file="s0014/s0014_07696_0_0_1_0_1_02.png" />
    <image file="s0014/s0014_07697_0_0_1_1_1_02.png" />
    <image file="s0014/s0014_07698_0_0_1_1_0_02.png" />
    <image file="s0014/s0014_07699_0_0_1_1_1_02.png" />
    <image file="s0014/s0014_07700_0_0_1_1_0_02.png" />
    <image file="s0014/s0014_07701_0_0_1_1_0_02.png" />
    <image file="s0014/s0014_07702_0_0_1_1_1_02.png" />
    <image file="s0014/s0014_07703_0_0_1_1_0_02.png" />
    <image file="s0014/s0014_07704_0_0_1_1_1_02.png" />
    <image file="s0014/s0014_07705_0_0_1_1_0_02.png" />
    <image file="s0014/s0014_07706_0_0_1_1_1_02.png" />
    <image file="s0014/s0014_07707_0_0_1_1_1_02.png" />
    <image file="s0014/s0014_07708_0_0_1_1_0_02.png" />
    <image file="s0014/s0014_07709_0_0_1_1_1_02.png" />
    <image file="s0014/s0014_07710_0_0_1_1_0_02.png" />
    <image file="s0014/s0014_07711_0_0_1_0_1_02.png" />
    <image file="s0014/s0014_07712_0_0_1_1_0_02.png" />
    <image file="s0014/s0014_07713_0_0_1_1_1_02.png" />
    <image file="s0014/s0014_07714_0_0_1_1_0_02.png" />
    <image file="s0014/s0014_07715_0_0_1_1_1_02.png" />
    <image file="s0014/s0014_07716_0_0_1_1_0_02.png" />
    <image file="s0014/s0014_07717_0_0_1_1_1_02.png" />
    <image file="s0014/s0014_07718_0_0_1_1_0_02.png" />
    <image file="s0014/s0014_07719_0_0_1_1_1_02.png" />
    <image file="s0014/s0014_07720_0_0_1_1_0_02.png" />
    <image file="s0014/s0014_07721_0_0_1_1_1_02.png" />
    <image file="s0014/s0014_07722_0_0_1_1_0_02.png" />
    <image file="s0014/s0014_07723_0_0_1_1_1_02.png" />
    <image file="s0014/s0014_07724_0_0_1_1_0_02.png" />
    <image file="s0014/s0014_07725_0_0_1_1_1_02.png" />
    <image file="s0014/s0014_07726_0_0_1_1_0_02.png" />
    <image file="s0014/s0014_07727_0_0_1_0_1_02.png" />
    <image file="s0014/s0014_07728_0_0_1_1_0_02.png" />
    <image file="s0014/s0014_07729_0_0_1_1_1_02.png" />
    <image file="s0014/s0014_07730_0_0_1_1_0_02.png" />
    <image file="s0014/s0014_07731_0_0_1_1_1_02.png" />
    <image file="s0014/s0014_07732_0_0_1_1_0_02.png" />
    <image file="s0014/s0014_07733_0_0_1_1_1_02.png" />
    <image file="s0014/s0014_07734_0_0_1_1_0_02.png" />
    <image file="s0014/s0014_07735_0_0_1_1_1_02.png" />
    <image file="s0014/s0014_07736_0_0_1_1_0_02.png" />
    <image file="s0014/s0014_07737_0_0_1_1_1_02.png" />
    <image file="s0014/s0014_07738_0_0_1_1_0_02.png" />
    <image file="s0014/s0014_07739_0_0_1_1_1_02.png" />
    <image file="s0014/s0014_07740_0_0_1_1_0_02.png" />
    <image file="s0014/s0014_07741_0_0_1_1_1_02.png" />
    <image file="s0014/s0014_07742_0_0_1_1_0_02.png" />
    <image file="s0014/s0014_07743_0_0_1_1_1_02.png" />
    <image file="s0014/s0014_07744_0_0_1_1_0_02.png" />
    <image file="s0014/s0014_07745_0_0_1_1_1_02.png" />
    <image file="s0014/s0014_07746_0_0_1_1_0_02.png" />
    <image file="s0014/s0014_07747_0_0_1_1_1_02.png" />
    <image file="s0014/s0014_07748_0_0_1_1_0_02.png" />
    <image file="s0014/s0014_07749_0_0_1_1_1_02.png" />
    <image file="s0014/s0014_07750_0_0_1_1_0_02.png" />
    <image file="s0014/s0014_07751_0_0_1_1_1_02.png" />
    <image file="s0014/s0014_07752_0_0_1_1_0_02.png" />
    <image file="s0014/s0014_07753_0_0_1_1_1_02.png" />
    <image file="s0014/s0014_07754_0_0_1_1_0_02.png" />
    <image file="s0014/s0014_07755_0_0_1_1_1_02.png" />
    <image file="s0014/s0014_07756_0_0_1_1_0_02.png" />
    <image file="s0014/s0014_07757_0_0_1_1_1_02.png" />
    <image file="s0014/s0014_07758_0_0_1_1_0_02.png" />
    <image file="s0014/s0014_07759_0_0_1_1_1_02.png" />
    <image file="s0014/s0014_07760_0_0_1_1_0_02.png" />
    <image file="s0014/s0014_07761_0_0_1_1_1_02.png" />
    <image file="s0014/s0014_07762_0_0_1_1_0_02.png" />
    <image file="s0014/s0014_07763_0_0_1_1_1_02.png" />
    <image file="s0014/s0014_07764_0_0_1_1_0_02.png" />
    <image file="s0014/s0014_07765_0_0_1_1_1_02.png" />
    <image file="s0014/s0014_07766_0_0_1_1_0_02.png" />
    <image file="s0014/s0014_07767_0_0_1_1_1_02.png" />
    <image file="s0014/s0014_07768_0_0_1_1_0_02.png" />
    <image file="s0014/s0014_07769_0_0_1_1_1_02.png" />
    <image file="s0014/s0014_07770_0_0_1_1_0_02.png" />
    <image file="s0014/s0014_07771_0_0_1_1_1_02.png" />
    <image file="s0014/s0014_07772_0_0_1_1_0_02.png" />
    <image file="s0014/s0014_07773_0_0_1_0_1_02.png" />
    <image file="s0014/s0014_07774_0_0_1_1_0_02.png" />
    <image file="s0014/s0014_07775_0_0_1_1_1_02.png" />
    <image file="s0014/s0014_07776_0_0_1_1_0_02.png" />
    <image file="s0014/s0014_07777_0_0_1_1_1_02.png" />
    <image file="s0014/s0014_07778_0_0_1_1_0_02.png" />
    <image file="s0014/s0014_07779_0_0_1_1_1_02.png" />
    <image file="s0014/s0014_07780_0_0_1_1_0_02.png" />
    <image file="s0014/s0014_07781_0_0_1_1_1_02.png" />
    <image file="s0014/s0014_07782_0_0_1_1_0_02.png" />
    <image file="s0014/s0014_07783_0_0_1_1_1_02.png" />
    <image file="s0014/s0014_07784_0_0_1_1_0_02.png" />
    <image file="s0014/s0014_07785_0_0_1_1_1_02.png" />
    <image file="s0014/s0014_07786_0_0_1_1_0_02.png" />
    <image file="s0014/s0014_07787_0_0_1_0_1_02.png" />
    <image file="s0014/s0014_07788_0_0_1_0_1_02.png" />
    <image file="s0014/s0014_07789_0_0_1_1_1_02.png" />
    <image file="s0014/s0014_07790_0_0_1_1_1_02.png" />
    <image file="s0014/s0014_07791_0_0_1_1_0_02.png" />
    <image file="s0014/s0014_07792_0_0_1_1_1_02.png" />
    <image file="s0014/s0014_07793_0_0_1_1_0_02.png" />
    <image file="s0014/s0014_07794_0_0_1_1_1_02.png" />
    <image file="s0014/s0014_07795_0_0_1_1_0_02.png" />
    <image file="s0014/s0014_07796_0_0_1_0_1_02.png" />
    <image file="s0014/s0014_07797_0_0_1_1_0_02.png" />
    <image file="s0014/s0014_07798_0_0_1_1_1_02.png" />
    <image file="s0014/s0014_07799_0_0_1_1_0_02.png" />
    <image file="s0014/s0014_07800_0_0_1_1_1_02.png" />
    <image file="s0014/s0014_07801_0_0_1_1_0_02.png" />
    <image file="s0014/s0014_07802_0_0_1_0_1_02.png" />
    <image file="s0014/s0014_07803_0_0_1_1_0_02.png" />
    <image file="s0014/s0014_07804_0_0_1_0_1_02.png" />
    <image file="s0014/s0014_07805_0_0_1_1_0_02.png" />
    <image file="s0014/s0014_07806_0_0_1_1_1_02.png" />
    <image file="s0014/s0014_07807_0_0_1_1_0_02.png" />
    <image file="s0014/s0014_07808_0_0_1_1_1_02.png" />
    <image file="s0014/s0014_07809_0_0_1_1_0_02.png" />
    <image file="s0014/s0014_07810_0_0_1_1_1_02.png" />
    <image file="s0014/s0014_07811_0_0_1_1_0_02.png" />
    <image file="s0014/s0014_07812_0_0_1_1_1_02.png" />
    <image file="s0014/s0014_07813_0_0_1_1_0_02.png" />
    <image file="s0014/s0014_07814_0_0_1_1_1_02.png" />
    <image file="s0014/s0014_07815_0_0_1_1_0_02.png" />
    <image file="s0014/s0014_07816_0_0_1_1_1_02.png" />
    <image file="s0014/s0014_07817_0_0_1_1_0_02.png" />
    <image file="s0014/s0014_07818_0_0_1_1_1_02.png" />
    <image file="s0014/s0014_07819_0_0_1_1_0_02.png" />
    <image file="s0014/s0014_07820_0_0_1_1_1_02.png" />
    <image file="s0014/s0014_07821_0_0_1_1_0_02.png" />
    <image file="s0014/s0014_07822_0_0_1_1_1_02.png" />
    <image file="s0014/s0014_07823_0_0_1_1_0_02.png" />
    <image file="s0014/s0014_07824_0_0_1_1_1_02.png" />
    <image file="s0014/s0014_07825_0_0_1_1_0_02.png" />
    <image file="s0014/s0014_07826_0_0_1_1_1_02.png" />
    <image file="s0014/s0014_07827_0_0_1_1_0_02.png" />
    <image file="s0014/s0014_07828_0_0_1_1_1_02.png" />
    <image file="s0014/s0014_07829_0_0_1_1_0_02.png" />
    <image file="s0014/s0014_07830_0_0_1_1_1_02.png" />
    <image file="s0014/s0014_07831_0_0_1_1_0_02.png" />
    <image file="s0014/s0014_07832_0_0_1_1_1_02.png" />
    <image file="s0014/s0014_07833_0_0_1_1_0_02.png" />
    <image file="s0014/s0014_07834_0_0_1_1_1_02.png" />
    <image file="s0014/s0014_07835_0_0_1_1_1_02.png" />
    <image file="s0014/s0014_07836_0_0_1_1_1_02.png" />
    <image file="s0014/s0014_07837_0_0_1_1_0_02.png" />
    <image file="s0014/s0014_07838_0_0_1_1_1_02.png" />
    <image file="s0014/s0014_07839_0_0_1_1_0_02.png" />
    <image file="s0014/s0014_07840_0_0_1_1_1_02.png" />
    <image file="s0014/s0014_07841_0_0_1_1_0_02.png" />
    <image file="s0014/s0014_07842_0_0_1_1_1_02.png" />
    <image file="s0014/s0014_07843_0_0_1_1_0_02.png" />
    <image file="s0014/s0014_07844_0_0_1_1_1_02.png" />
    <image file="s0014/s0014_07845_0_0_1_1_0_02.png" />
    <image file="s0014/s0014_07846_0_0_1_1_1_02.png" />
    <image file="s0014/s0014_07847_0_0_1_1_0_02.png" />
    <image file="s0014/s0014_07848_0_0_1_1_1_02.png" />
    <image file="s0014/s0014_07849_0_0_1_1_0_02.png" />
    <image file="s0014/s0014_07850_0_0_1_1_1_02.png" />
    <image file="s0014/s0014_07851_0_0_1_1_0_02.png" />
    <image file="s0014/s0014_07852_0_0_1_1_1_02.png" />
    <image file="s0014/s0014_07853_0_0_1_1_0_02.png" />
    <image file="s0014/s0014_07854_0_0_1_1_1_02.png" />
    <image file="s0014/s0014_07855_0_0_1_1_0_02.png" />
    <image file="s0014/s0014_07856_0_0_1_1_1_02.png" />
    <image file="s0014/s0014_07857_0_0_1_1_0_02.png" />
    <image file="s0014/s0014_07858_0_0_1_1_1_02.png" />
    <image file="s0014/s0014_07859_0_0_1_1_0_02.png" />
    <image file="s0014/s0014_07860_0_0_1_1_1_02.png" />
    <image file="s0014/s0014_07861_0_0_1_1_0_02.png" />
    <image file="s0014/s0014_07862_0_0_1_1_1_02.png" />
    <image file="s0014/s0014_07863_0_0_1_1_0_02.png" />
    <image file="s0014/s0014_07864_0_0_1_1_1_02.png" />
    <image file="s0014/s0014_07865_0_0_1_1_0_02.png" />
    <image file="s0014/s0014_07866_0_0_1_1_1_02.png" />
    <image file="s0014/s0014_07867_0_0_1_1_0_02.png" />
    <image file="s0014/s0014_07868_0_0_1_1_1_02.png" />
    <image file="s0014/s0014_07869_0_0_1_1_0_02.png" />
    <image file="s0014/s0014_07870_0_0_1_1_1_02.png" />
    <image file="s0014/s0014_07871_0_0_1_1_0_02.png" />
    <image file="s0014/s0014_07872_0_0_1_1_1_02.png" />
    <image file="s0014/s0014_07873_0_0_1_1_0_02.png" />
    <image file="s0014/s0014_07874_0_0_1_1_1_02.png" />
    <image file="s0014/s0014_07875_0_0_1_1_0_02.png" />
    <image file="s0014/s0014_07876_0_0_1_1_1_02.png" />
    <image file="s0014/s0014_07877_0_0_1_1_0_02.png" />
    <image file="s0014/s0014_07878_0_0_1_1_1_02.png" />
    <image file="s0014/s0014_07879_0_0_1_1_0_02.png" />
    <image file="s0014/s0014_07880_0_0_1_1_1_02.png" />
    <image file="s0014/s0014_07881_0_0_1_1_0_02.png" />
    <image file="s0014/s0014_07882_0_0_1_1_1_02.png" />
    <image file="s0014/s0014_07883_0_0_1_1_0_02.png" />
    <image file="s0014/s0014_07884_0_0_1_1_1_02.png" />
    <image file="s0014/s0014_07885_0_0_1_1_0_02.png" />
    <image file="s0014/s0014_07886_0_0_1_1_1_02.png" />
    <image file="s0014/s0014_07887_0_0_1_1_0_02.png" />
    <image file="s0014/s0014_07888_0_0_1_1_1_02.png" />
    <image file="s0014/s0014_07889_0_0_1_1_0_02.png" />
    <image file="s0014/s0014_07890_0_0_1_1_1_02.png" />
    <image file="s0014/s0014_07891_0_0_1_1_0_02.png" />
    <image file="s0014/s0014_07892_0_0_1_1_1_02.png" />
    <image file="s0014/s0014_07893_0_0_1_1_0_02.png" />
    <image file="s0014/s0014_07894_0_0_1_1_1_02.png" />
    <image file="s0014/s0014_07895_0_0_1_1_0_02.png" />
    <image file="s0014/s0014_07896_0_0_1_1_1_02.png" />
    <image file="s0014/s0014_07897_0_0_1_1_0_02.png" />
    <image file="s0014/s0014_07898_0_0_1_1_1_02.png" />
    <image file="s0014/s0014_07899_0_0_1_1_0_02.png" />
    <image file="s0014/s0014_07900_0_0_1_1_1_02.png" />
    <image file="s0014/s0014_07901_0_0_1_1_0_02.png" />
    <image file="s0014/s0014_07902_0_0_1_1_1_02.png" />
    <image file="s0014/s0014_07903_0_0_1_1_0_02.png" />
    <image file="s0014/s0014_07904_0_0_1_1_1_02.png" />
    <image file="s0014/s0014_07905_0_0_1_1_0_02.png" />
    <image file="s0014/s0014_07906_0_0_1_1_1_02.png" />
    <image file="s0014/s0014_07907_0_0_1_1_0_02.png" />
    <image file="s0014/s0014_07908_0_0_1_1_1_02.png" />
    <image file="s0014/s0014_07909_0_0_1_1_0_02.png" />
    <image file="s0014/s0014_07910_0_0_1_1_1_02.png" />
    <image file="s0014/s0014_07911_0_0_1_1_0_02.png" />
    <image file="s0014/s0014_07912_0_0_1_1_1_02.png" />
    <image file="s0014/s0014_07913_0_0_1_1_0_02.png" />
    <image file="s0014/s0014_07914_0_0_1_1_1_02.png" />
    <image file="s0014/s0014_07915_0_0_1_1_0_02.png" />
    <image file="s0014/s0014_07916_0_0_1_1_1_02.png" />
    <image file="s0014/s0014_07917_0_0_1_1_0_02.png" />
    <image file="s0014/s0014_07918_0_0_1_1_1_02.png" />
    <image file="s0014/s0014_07919_0_0_1_1_0_02.png" />
    <image file="s0014/s0014_07920_0_0_1_1_1_02.png" />
    <image file="s0014/s0014_07921_0_0_1_1_0_02.png" />
    <image file="s0014/s0014_07922_0_0_1_1_1_02.png" />
    <image file="s0014/s0014_07923_0_0_1_1_0_02.png" />
    <image file="s0014/s0014_07924_0_0_1_1_1_02.png" />
    <image file="s0014/s0014_07925_0_0_1_1_0_02.png" />
    <image file="s0014/s0014_07926_0_0_1_1_1_02.png" />
    <image file="s0014/s0014_07927_0_0_1_1_0_02.png" />
    <image file="s0014/s0014_07928_0_0_1_1_1_02.png" />
    <image file="s0014/s0014_07929_0_0_1_1_0_02.png" />
    <image file="s0014/s0014_07930_0_0_1_1_1_02.png" />
    <image file="s0014/s0014_07931_0_0_1_1_0_02.png" />
    <image file="s0014/s0014_07932_0_0_1_1_1_02.png" />
    <image file="s0014/s0014_07933_0_0_1_1_0_02.png" />
    <image file="s0014/s0014_07934_0_0_1_1_1_02.png" />
    <image file="s0014/s0014_07935_0_0_1_1_0_02.png" />
    <image file="s0014/s0014_07936_0_0_1_1_1_02.png" />
    <image file="s0014/s0014_07937_0_0_1_1_0_02.png" />
    <image file="s0014/s0014_07938_0_0_1_1_1_02.png" />
    <image file="s0014/s0014_07939_0_0_1_1_0_02.png" />
    <image file="s0014/s0014_07940_0_0_1_1_1_02.png" />
    <image file="s0014/s0014_07941_0_0_1_1_0_02.png" />
    <image file="s0014/s0014_07942_0_0_1_1_1_02.png" />
    <image file="s0014/s0014_07943_0_0_1_1_0_02.png" />
    <image file="s0014/s0014_07944_0_0_1_1_1_02.png" />
    <image file="s0014/s0014_07945_0_0_1_1_0_02.png" />
    <image file="s0014/s0014_07946_0_0_1_1_1_02.png" />
    <image file="s0014/s0014_07947_0_0_1_1_0_02.png" />
    <image file="s0014/s0014_07948_0_0_1_1_1_02.png" />
    <image file="s0014/s0014_07949_0_0_1_1_0_02.png" />
    <image file="s0014/s0014_07950_0_0_1_1_1_02.png" />
    <image file="s0014/s0014_07951_0_0_1_1_0_02.png" />
    <image file="s0014/s0014_07952_0_0_1_1_1_02.png" />
    <image file="s0014/s0014_07953_0_0_1_1_0_02.png" />
    <image file="s0014/s0014_07954_0_0_1_1_1_02.png" />
    <image file="s0014/s0014_07955_0_0_1_1_0_02.png" />
    <image file="s0014/s0014_07956_0_0_1_1_1_02.png" />
    <image file="s0014/s0014_07957_0_0_1_1_0_02.png" />
    <image file="s0014/s0014_07958_0_0_1_1_1_02.png" />
    <image file="s0014/s0014_07959_0_0_1_1_0_02.png" />
    <image file="s0014/s0014_07960_0_0_1_1_1_02.png" />
    <image file="s0014/s0014_07961_0_0_1_1_0_02.png" />
    <image file="s0014/s0014_07962_0_0_1_1_1_02.png" />
    <image file="s0014/s0014_07963_0_0_1_1_0_02.png" />
    <image file="s0014/s0014_07964_0_0_1_1_1_02.png" />
    <image file="s0014/s0014_07965_0_0_1_1_0_02.png" />
    <image file="s0014/s0014_07966_0_0_1_1_1_02.png" />
    <image file="s0014/s0014_07967_0_0_1_1_0_02.png" />
    <image file="s0014/s0014_07968_0_0_1_1_1_02.png" />
    <image file="s0014/s0014_07969_0_0_1_1_0_02.png" />
    <image file="s0014/s0014_07970_0_0_1_1_1_02.png" />
    <image file="s0014/s0014_07971_0_0_1_1_0_02.png" />
    <image file="s0014/s0014_07972_0_0_1_1_1_02.png" />
  </images>
</dataset>
